yoni_bmi_calculator/__init__.py
yoni_bmi_calculator/bmi_calculator.py
yoni_bmi_calculator/yoni_bmi_calculator/__init__.py
yoni_bmi_calculator-1.0.0.dist-info/licenses/LICENSE
yoni_bmi_calculator-1.0.0.dist-info/METADATA
yoni_bmi_calculator-1.0.0.dist-info/WHEEL
yoni_bmi_calculator-1.0.0.dist-info/top_level.txt
yoni_bmi_calculator-1.0.0.dist-info/RECORD
