Metadata-Version: 2.4
Name: yoni-bmi-calculator
Version: 1.0.0
Summary: A comprehensive BMI calculator with health interpretations and unit conversions
Home-page: https://github.com/23soni23/yoni-bmi-calculator
Author: Yoni
Author-email: Yoni <yoni@example.com>
License: MIT
Project-URL: Homepage, https://github.com/23soni23/yoni-bmi-calculator
Project-URL: Bug Tracker, https://github.com/23soni23/yoni-bmi-calculator/issues
Project-URL: Documentation, https://github.com/23soni23/yoni-bmi-calculator#readme
Keywords: bmi,calculator,health,fitness,body mass index,weight,height,metric,imperial
Classifier: Development Status :: 5 - Production/Stable
Classifier: Intended Audience :: Developers
Classifier: Intended Audience :: Healthcare Industry
Classifier: Topic :: Scientific/Engineering :: Medical Science Apps.
Classifier: Topic :: Software Development :: Libraries :: Python Modules
Classifier: License :: OSI Approved :: MIT License
Classifier: Programming Language :: Python :: 3
Classifier: Programming Language :: Python :: 3.7
Classifier: Programming Language :: Python :: 3.8
Classifier: Programming Language :: Python :: 3.9
Classifier: Programming Language :: Python :: 3.10
Classifier: Programming Language :: Python :: 3.11
Classifier: Programming Language :: Python :: 3.12
Classifier: Operating System :: OS Independent
Requires-Python: >=3.7
License-File: LICENSE
Dynamic: author
Dynamic: home-page
Dynamic: license-file
Dynamic: requires-python
